Workbook

Sheet Sheet1
A1: United States | C1: Data Source | D1: Year | E1: Unit | F1: 2023 | G1: 2024 | H1: 2025 | I1: 2026 | J1: 2027 | K1: 2028 | L1: 2029 | M1: 2030 | N1: 2031 | O1: 2032 | P1: 2033 | Q1: 2034 | R1: 2035 | T1: Notes
B3: Financial | C3: bnef lcoe data viewer tool | D3: Cost of equity (%) | F3: 0.085 | G3: 0.081266165 | H3: 0.079158515 | I3: 0.077696348 | J3: 0.076580828 | K3: 0.075681282 | L3: 0.074928975 | M3: 0.074283344 | N3: 0.073718477 | O3: 0.073216826 | P3: 0.07276597 | Q3: 0.072356795 | R3: 0.071982422
C4: bnef lcoe data viewer tool | D4: Cost of debt (bps) | F4: 621 | G4: 576.30498 | H4: 551.66654 | I4: 534.82679 | J4: 522.11967 | K4: 511.96164 | L4: 503.52749 | M4: 496.33389 | N4: 490.07403 | O4: 484.54133 | P4: 479.59022 | Q4: 475.1144 | R4: 471.03394
C5: bnef lcoe data viewer tool | D5: Debt ratio (%) | F5: 0.7001 | G5: 0.7001 | H5: 0.7001 | I5: 0.7001 | J5: 0.7001 | K5: 0.7001 | L5: 0.7001 | M5: 0.7001 | N5: 0.7001 | O5: 0.7001 | P5: 0.7001 | Q5: 0.7001 | R5: 0.7001
C6: bnef lcoe data viewer tool | D6: WACC | F6: 0.06896771 | G6: 0.064718835 | H6: 0.062361813 | I6: 0.060744358 | J6: 0.059520188 | K6: 0.058539251 | L6: 0.057723159 | M6: 0.05702591 | N6: 0.056418254 | O6: 0.055880465 | P6: 0.055398626 | Q6: 0.054962562 | R6: 0.054564615
C7: bnef lcoe data viewer tool | D7: Economic life (yrs) | F7: 25 | G7: 25 | H7: 25 | I7: 25 | J7: 25 | K7: 25 | L7: 25 | M7: 25 | N7: 25 | O7: 25 | P7: 25 | Q7: 25 | R7: 25
A9: 22 US$ | B9: Solar | C9: bnef lcoe data viewer tool | D9: Capex | E9: $/kW | F9: 1034.3987 | G9: 920.11132 | H9: 833.24418 | I9: 792.0763 | J9: 755.05522 | K9: 725.01053 | L9: 697.85656 | M9: 689.20253 | N9: 626.56538 | O9: 563.92823 | P9: 501.29108 | Q9: 438.65393 | R9: 376.01678 | T9: mid scenario
A10: 22 US$ | C10: bnef lcoe data viewer tool | D10: Fixed O&M | E10: $/MW/yr | F10: 15785.332 | G10: 15463.57 | H10: 15103.484 | I10: 14871.148 | J10: 14637.407 | K10: 14501.164 | L10: 14306.29 | M10: 14083.441 | N10: 13919.521 | O10: 13776.053 | P10: 13649.701 | Q10: 13536.54 | R10: 13432.892 | T10: mid scenario
A12: 22 US$ | B12: Storage | C12: bnef lcoe data viewer tool | D12: Fixed O&M | E12: $/MW/yr | F12: 3296.6639 | G12: 2773.6115 | H12: 2567.7979 | I12: 2399.3912 | J12: 2258.4608 | K12: 2138.1071 | L12: 2031.1079 | M12: 1942.4719 | N12: 1864.0491 | O12: 1793.3602 | P12: 1748.7163 | Q12: 1705.195 | R12: 1662.6651 | T12: mid scenario
A13: 24 US$ | C13: from bnef energy storage system cost survey 2024 | D13: Rack+pack | E13: $/kWh | F13: 174.21851 | G13: 132.05962 | H13: 128.61459 | I13: 112.73406 | J13: 96.853524 | K13: 89.924459 | L13: 84.116192 | M13: 79.168151 | N13: 74.877079 | O13: 71.13885 | P13: 67.846919 | Q13: 64.943163 | R13: 62.357634 | T13: global benchmark, avg of high and low cost scenarios, 4hr duration
A14: 24 US$ | C14: from bnef li battery price survey | D14: Pack | E14: $/kWh | F14: 144 | G14: 115 | H14: 100 | I14: 91 | J14: 84 | K14: 78 | L14: 73 | M14: 69 | N14: 65 | O14: 62 | P14: 59 | Q14: 57 | R14: 54
A15: 24 US$ | C15: from bnef energy storage system cost survey 2024 | D15: Rack | E15: $/kWh | F15: =F13-F14 -> 30.218513 | G15: =G13-G14 -> 17.05962 | H15: =H13-H14 -> 28.614587 | I15: =I13-I14 -> 21.734056 | J15: =J13-J14 -> 12.853524 | K15: =K13-K14 -> 11.924459 | L15: =L13-L14 -> 11.116192 | M15: =M13-M14 -> 10.168151 | ... R15: =R13-R14 -> 8.3576342
A16: 24 US$ | C16: from bnef energy storage system cost survey 2024 | D16: BOS + EMS | E16: $/kWh | F16: 43.551076 | G16: 35.482861 | H16: 33.983124 | I16: 32.726894 | J16: 31.594097 | K16: 30.593897 | L16: 29.736114 | M16: 28.987324 | N16: 28.323051 | O16: 27.734237 | P16: 27.190636 | Q16: 26.680058 | R16: 25.961164 | T16: global benchmark, avg of high and low cost scenarios, 4hr duration
A17: 24 US$ | C17: from bnef energy storage system cost survey 2024 | D17: PCS + EPC + Overhead | E17: $/kW | F17: 276.63349 | G17: 317.78013 | H17: 304.00978 | I17: 292.4903 | J17: 282.11436 | K17: 272.96253 | L17: 265.12124 | M17: 258.28197 | N17: 252.21916 | O17: 246.84865 | P17: 241.8935 | Q17: 237.24201 | R17: 230.69624 | T17: global benchmark, avg of high and low cost scenarios, 4hr duration

Sheet 2025US$
A1: United States | C1: Data Source | D1: Year | E1: Unit | F1: 2023 | G1: 2024 | H1: 2025 | I1: 2026 | J1: 2027 | K1: 2028 | L1: 2029 | M1: 2030 | N1: 2031 | O1: 2032 | P1: 2033 | Q1: 2034 | R1: 2035 | T1: Notes
B3: Financial | C3: bnef lcoe data viewer tool | D3: Cost of equity (%) | F3: 0.085 | G3: 0.081266165 | H3: 0.079158515 | I3: 0.077696348 | J3: 0.076580828 | K3: 0.075681282 | L3: 0.074928975 | M3: 0.074283344 | N3: 0.073718477 | O3: 0.073216826 | P3: 0.07276597 | Q3: 0.072356795 | R3: 0.071982422
C4: bnef lcoe data viewer tool | D4: Cost of debt (bps) | F4: 621 | G4: 576.30498 | H4: 551.66654 | I4: 534.82679 | J4: 522.11967 | K4: 511.96164 | L4: 503.52749 | M4: 496.33389 | N4: 490.07403 | O4: 484.54133 | P4: 479.59022 | Q4: 475.1144 | R4: 471.03394
C5: bnef lcoe data viewer tool | D5: Debt ratio (%) | F5: 0.7001 | G5: 0.7001 | H5: 0.7001 | I5: 0.7001 | J5: 0.7001 | K5: 0.7001 | L5: 0.7001 | M5: 0.7001 | N5: 0.7001 | O5: 0.7001 | P5: 0.7001 | Q5: 0.7001 | R5: 0.7001
C6: bnef lcoe data viewer tool | D6: WACC | F6: 0.06896771 | G6: 0.064718835 | H6: 0.062361813 | I6: 0.060744358 | J6: 0.059520188 | K6: 0.058539251 | L6: 0.057723159 | M6: 0.05702591 | N6: 0.056418254 | O6: 0.055880465 | P6: 0.055398626 | Q6: 0.054962562 | R6: 0.054564615
C7: bnef lcoe data viewer tool | D7: Economic life (yrs) | F7: 25 | G7: 25 | H7: 25 | I7: 25 | J7: 25 | K7: 25 | L7: 25 | M7: 25 | N7: 25 | O7: 25 | P7: 25 | Q7: 25 | R7: 25
A9: 22 US$ | B9: Solar | C9: bnef lcoe data viewer tool | D9: Capex | E9: $/kW | F9: =Sheet1!F9*'2025US$'!$B$20 -> 1148.1825 | G9: =Sheet1!G9*'2025US$'!$B$20 -> 1021.3236 | H9: =Sheet1!H9*'2025US$'!$B$20 -> 924.90103 | I9: =Sheet1!I9*'2025US$'!$B$20 -> 879.20469 | J9: =Sheet1!J9*'2025US$'!$B$20 -> 838.11129 | K9: =Sheet1!K9*'2025US$'!$B$20 -> 804.76169 | L9: =Sheet1!L9*'2025US$'!$B$20 -> 774.62079 | M9: =Sheet1!M9*'2025US$'!$B$20 -> 765.01481 | ... R9: =Sheet1!R9*'2025US$'!$B$20 -> 417.37862 | T9: mid scenario
A10: 22 US$ | C10: bnef lcoe data viewer tool | D10: Fixed O&M | E10: $/MW/yr | F10: =Sheet1!F10*'2025US$'!$B$20 -> 17521.718 | G10: =Sheet1!G10*'2025US$'!$B$20 -> 17164.563 | H10: =Sheet1!H10*'2025US$'!$B$20 -> 16764.868 | I10: =Sheet1!I10*'2025US$'!$B$20 -> 16506.974 | J10: =Sheet1!J10*'2025US$'!$B$20 -> 16247.522 | K10: =Sheet1!K10*'2025US$'!$B$20 -> 16096.292 | L10: =Sheet1!L10*'2025US$'!$B$20 -> 15879.982 | M10: =Sheet1!M10*'2025US$'!$B$20 -> 15632.619 | ... R10: =Sheet1!R10*'2025US$'!$B$20 -> 14910.511 | T10: mid scenario
A12: 22 US$ | B12: Storage | C12: bnef lcoe data viewer tool | D12: Fixed O&M | E12: $/MW/yr | F12: =Sheet1!F12*'2025US$'!$B$20 -> 3659.2969 | G12: =Sheet1!G12*'2025US$'!$B$20 -> 3078.7088 | H12: =Sheet1!H12*'2025US$'!$B$20 -> 2850.2556 | I12: =Sheet1!I12*'2025US$'!$B$20 -> 2663.3243 | J12: =Sheet1!J12*'2025US$'!$B$20 -> 2506.8915 | K12: =Sheet1!K12*'2025US$'!$B$20 -> 2373.2989 | L12: =Sheet1!L12*'2025US$'!$B$20 -> 2254.5298 | M12: =Sheet1!M12*'2025US$'!$B$20 -> 2156.1438 | ... R12: =Sheet1!R12*'2025US$'!$B$20 -> 1845.5582 | T12: mid scenario
A13: 24 US$ | C13: from bnef energy storage system cost survey 2024 | D13: Rack+pack | E13: $/kWh | F13: =Sheet1!F13*'2025US$'!$B$21 -> 180.31616 | G13: =Sheet1!G13*'2025US$'!$B$21 -> 136.68171 | H13: =Sheet1!H13*'2025US$'!$B$21 -> 133.1161 | I13: =Sheet1!I13*'2025US$'!$B$21 -> 116.67975 | J13: =Sheet1!J13*'2025US$'!$B$21 -> 100.2434 | K13: =Sheet1!K13*'2025US$'!$B$21 -> 93.071815 | L13: =Sheet1!L13*'2025US$'!$B$21 -> 87.060259 | M13: =Sheet1!M13*'2025US$'!$B$21 -> 81.939036 | ... R13: =Sheet1!R13*'2025US$'!$B$21 -> 64.540151 | T13: global benchmark, avg of high and low cost scenarios, 4hr duration
A14: 24 US$ | C14: from bnef li battery price survey | D14: Pack | E14: $/kWh | F14: =Sheet1!F14*'2025US$'!$B$21 -> 149.04 | G14: =Sheet1!G14*'2025US$'!$B$21 -> 119.025 | H14: =Sheet1!H14*'2025US$'!$B$21 -> 103.5 | I14: =Sheet1!I14*'2025US$'!$B$21 -> 94.185 | J14: =Sheet1!J14*'2025US$'!$B$21 -> 86.94 | K14: =Sheet1!K14*'2025US$'!$B$21 -> 80.73 | L14: =Sheet1!L14*'2025US$'!$B$21 -> 75.555 | M14: =Sheet1!M14*'2025US$'!$B$21 -> 71.415 | ... R14: =Sheet1!R14*'2025US$'!$B$21 -> 55.89
A15: 24 US$ | C15: from bnef energy storage system cost survey 2024 | D15: Rack | E15: $/kWh | F15: =F13-F14 -> 31.276161 | G15: =G13-G14 -> 17.656707 | H15: =H13-H14 -> 29.616097 | I15: =I13-I14 -> 22.494747 | J15: =J13-J14 -> 13.303398 | K15: =K13-K14 -> 12.341815 | L15: =L13-L14 -> 11.505259 | M15: =M13-M14 -> 10.524036 | ... R15: =R13-R14 -> 8.6501514
A16: 24 US$ | C16: from bnef energy storage system cost survey 2024 | D16: BOS + EMS | E16: $/kWh | F16: =Sheet1!F16*'2025US$'!$B$21 -> 45.075364 | G16: =Sheet1!G16*'2025US$'!$B$21 -> 36.724761 | H16: =Sheet1!H16*'2025US$'!$B$21 -> 35.172533 | I16: =Sheet1!I16*'2025US$'!$B$21 -> 33.872336 | J16: =Sheet1!J16*'2025US$'!$B$21 -> 32.69989 | K16: =Sheet1!K16*'2025US$'!$B$21 -> 31.664683 | L16: =Sheet1!L16*'2025US$'!$B$21 -> 30.776878 | M16: =Sheet1!M16*'2025US$'!$B$21 -> 30.00188 | ... R16: =Sheet1!R16*'2025US$'!$B$21 -> 26.869805 | T16: global benchmark, avg of high and low cost scenarios, 4hr duration
A17: 24 US$ | C17: from bnef energy storage system cost survey 2025 | D17: EPC | E17: $/kWh | F17: 42.136301 | G17: 53.897397 | H17: 51.619342 | I17: 49.711167 | J17: 47.990482 | K17: 46.471208 | L17: 45.168261 | M17: 44.030872 | N17: 43.021862 | O17: 42.127471 | P17: 41.301757 | Q17: 40.526204 | R17: 39.434226 | T17: global benchmark, avg of high and low cost scenarios, 4hr duration
C18: from bnef energy storage system cost survey 2024 | D18: PCS + Overhead | E18: $/kW | F18: 108.08828 | G18: 102.19055 | H18: 97.532408 | I18: 93.645629 | J18: 90.152438 | K18: 87.077701 | L18: 84.448194 | M18: 82.158486 | N18: 80.13171 | O18: 78.338761 | P18: 76.686473 | Q18: 75.137193 | R18: 72.95934 | T18: global benchmark, avg of high and low cost scenarios, 4hr duration corrected
A19: US$ conversion
A20: 2022>25 | B20: 1.11
A21: 2024->25 | B21: 1.035
A23: Pack | B23: Lithium battery cells
A24: Rack | B24: shelving, wiring, thermal cells
A25: BOS + EMS | B25: balance of systems, energy management systems
A26: EPC | B26: engineering, procurement, construction
A27: PCS + Overhead | B27: power conversion systems
